marathon_device_service/__init__.py
marathon_device_service/service.py
marathon_device_service-0.0.2.dist-info/METADATA
marathon_device_service-0.0.2.dist-info/WHEEL
marathon_device_service-0.0.2.dist-info/top_level.txt
marathon_device_service-0.0.2.dist-info/RECORD
