Metadata-Version: 2.1
Name: marathon-device-service
Version: 0.0.2
Summary: A Python library to manage a device in Marathon Cloud.
Home-page: https://marathonlabs.io
Author: MarathonLabs
Author-email: em@marathonlabs.io
License: UNKNOWN
Keywords: camera media upload service Marathon Cloud device emulator Android
Platform: UNKNOWN
Classifier: Programming Language :: Python :: 3
Classifier: Operating System :: OS Independent
Requires-Python: >=3.6
Requires-Dist: python-magic
Requires-Dist: requests
